llama_index/vector_stores/zeusdb/__init__.py
llama_index/vector_stores/zeusdb/base.py
llama_index/vector_stores/zeusdb/py.typed
llama_index_vector_stores_zeusdb-0.1.2.dist-info/METADATA
llama_index_vector_stores_zeusdb-0.1.2.dist-info/WHEEL
llama_index_vector_stores_zeusdb-0.1.2.dist-info/licenses/LICENSE
llama_index_vector_stores_zeusdb-0.1.2.dist-info/RECORD
