Metadata-Version: 2.4
Name: llama-index-vector-stores-zeusdb
Version: 0.1.2
Summary: LlamaIndex integration for ZeusDB vector database. Enterprise-grade RAG with high-performance vector search.
Project-URL: Homepage, https://github.com/zeusdb/llama-index-vector-stores-zeusdb
Project-URL: Repository, https://github.com/zeusdb/llama-index-vector-stores-zeusdb
Project-URL: Issues, https://github.com/zeusdb/llama-index-vector-stores-zeusdb/issues
Author-email: ZeusDB <contact@zeusdb.com>
License: MIT
License-File: LICENSE
Keywords: embeddings,hnsw,llama-index,rag,semantic-search,vector-database,zeusdb
Classifier: Intended Audience :: Developers
Classifier: License :: OSI Approved :: MIT License
Classifier: Programming Language :: Python :: 3.10
Classifier: Programming Language :: Python :: 3.11
Classifier: Programming Language :: Python :: 3.12
Classifier: Programming Language :: Python :: 3.13
Classifier: Topic :: Scientific/Engineering :: Artificial Intelligence
Classifier: Topic :: Software Development :: Libraries :: Python Modules
Requires-Python: <4.0,>=3.10
Requires-Dist: llama-index-core>=0.14.4
Requires-Dist: zeusdb>=0.0.8
Provides-Extra: dev
Requires-Dist: black>=25.1; extra == 'dev'
Requires-Dist: codespell[toml]>=2.2.6; extra == 'dev'
Requires-Dist: ipython>=8.10.0; extra == 'dev'
Requires-Dist: jupyter>=1.0.0; extra == 'dev'
Requires-Dist: llama-index-embeddings-openai>=0.5.1; extra == 'dev'
Requires-Dist: llama-index-llms-openai>=0.6.4; extra == 'dev'
Requires-Dist: mypy>=1.17; extra == 'dev'
Requires-Dist: pre-commit>=4.3; extra == 'dev'
Requires-Dist: pylint>=3.3; extra == 'dev'
Requires-Dist: pytest-asyncio>=1.2.0; extra == 'dev'
Requires-Dist: pytest-mock>=3.15; extra == 'dev'
Requires-Dist: pytest>=8.4; extra == 'dev'
Requires-Dist: python-dotenv>=1.1.1; extra == 'dev'
Requires-Dist: ruff>=0.12; extra == 'dev'
Requires-Dist: types-requests>=2.32; extra == 'dev'
